bibparse/__init__.py
bibparse-1.2.0.dist-info/LICENSE
bibparse-1.2.0.dist-info/METADATA
bibparse-1.2.0.dist-info/WHEEL
bibparse-1.2.0.dist-info/top_level.txt
bibparse-1.2.0.dist-info/RECORD
