Metadata-Version: 2.1
Name: bibparse
Version: 1.2.0
Summary: Read and write BibTeX files
Home-page: http://github.com/Legisign/bibparse
Author: Legisign.org
Author-email: software@legisign.org
License: GPLv3
License-File: LICENSE
